agent_enforcer-0.9.0.dist-info/licenses/LICENSE
enforcer/__init__.py
enforcer/cli.py
enforcer/config.py
enforcer/core.py
enforcer/main.py
enforcer/mcp_server.py
enforcer/presenter.py
enforcer/utils.py
enforcer/plugins/__init__.py
enforcer/plugins/csharp.py
enforcer/plugins/js_ts.py
enforcer/plugins/kotlin.py
enforcer/plugins/python.py
agent_enforcer-0.9.0.dist-info/METADATA
agent_enforcer-0.9.0.dist-info/WHEEL
agent_enforcer-0.9.0.dist-info/entry_points.txt
agent_enforcer-0.9.0.dist-info/top_level.txt
agent_enforcer-0.9.0.dist-info/RECORD
