Metadata-Version: 2.4
Name: agent-enforcer
Version: 0.9.0
Summary: Agent Enforcer: A modular code quality checking tool
Author-email: Artemonim <artemonim@yandex.ru>
License-Expression: MIT
Project-URL: Homepage, https://github.com/Artemonim/AgentEnforcer
Project-URL: Source, https://github.com/Artemonim/AgentEnforcer
Project-URL: Tracker, https://github.com/Artemonim/AgentEnforcer/issues
Project-URL: Documentation, https://github.com/Artemonim/AgentEnforcer#readme
Project-URL: Changelog, https://github.com/Artemonim/AgentEnforcer/blob/master/CHANGELOG.md
Requires-Python: >=3.7
License-File: LICENSE
Requires-Dist: gitignore-parser
Requires-Dist: black
Requires-Dist: isort
Requires-Dist: flake8
Requires-Dist: mypy
Requires-Dist: pyright
Requires-Dist: pytest
Requires-Dist: pytest-asyncio
Requires-Dist: pytest-cov
Requires-Dist: fastmcp
Provides-Extra: dev
Requires-Dist: pytest>=6.0; extra == "dev"
Requires-Dist: pytest-asyncio>=1.0; extra == "dev"
Requires-Dist: pytest-cov>=4.0; extra == "dev"
Requires-Dist: black>=22.0; extra == "dev"
Requires-Dist: flake8>=4.0; extra == "dev"
Requires-Dist: mypy>=0.950; extra == "dev"
Requires-Dist: isort>=5.0; extra == "dev"
Dynamic: license-file
